clickhouse_connect/__init__.py
clickhouse_connect/__version__.py
clickhouse_connect/common.py
clickhouse_connect/entry_points.py
clickhouse_connect/json_impl.py
clickhouse_connect/py.typed
clickhouse_connect/cc_sqlalchemy/__init__.py
clickhouse_connect/cc_sqlalchemy/dialect.py
clickhouse_connect/cc_sqlalchemy/inspector.py
clickhouse_connect/cc_sqlalchemy/datatypes/__init__.py
clickhouse_connect/cc_sqlalchemy/datatypes/base.py
clickhouse_connect/cc_sqlalchemy/datatypes/sqltypes.py
clickhouse_connect/cc_sqlalchemy/ddl/__init__.py
clickhouse_connect/cc_sqlalchemy/ddl/custom.py
clickhouse_connect/cc_sqlalchemy/ddl/tableengine.py
clickhouse_connect/cc_sqlalchemy/sql/__init__.py
clickhouse_connect/cc_sqlalchemy/sql/clauses.py
clickhouse_connect/cc_sqlalchemy/sql/compiler.py
clickhouse_connect/cc_sqlalchemy/sql/ddlcompiler.py
clickhouse_connect/cc_sqlalchemy/sql/preparer.py
clickhouse_connect/datatypes/__init__.py
clickhouse_connect/datatypes/base.py
clickhouse_connect/datatypes/container.py
clickhouse_connect/datatypes/dynamic.py
clickhouse_connect/datatypes/format.py
clickhouse_connect/datatypes/geometric.py
clickhouse_connect/datatypes/network.py
clickhouse_connect/datatypes/numeric.py
clickhouse_connect/datatypes/postinit.py
clickhouse_connect/datatypes/registry.py
clickhouse_connect/datatypes/special.py
clickhouse_connect/datatypes/string.py
clickhouse_connect/datatypes/temporal.py
clickhouse_connect/dbapi/__init__.py
clickhouse_connect/dbapi/connection.py
clickhouse_connect/dbapi/cursor.py
clickhouse_connect/driver/__init__.py
clickhouse_connect/driver/asyncclient.py
clickhouse_connect/driver/binding.py
clickhouse_connect/driver/buffer.py
clickhouse_connect/driver/client.py
clickhouse_connect/driver/common.py
clickhouse_connect/driver/compression.py
clickhouse_connect/driver/constants.py
clickhouse_connect/driver/context.py
clickhouse_connect/driver/ctypes.py
clickhouse_connect/driver/dataconv.py
clickhouse_connect/driver/ddl.py
clickhouse_connect/driver/errors.py
clickhouse_connect-0.10.0.dist-info/licenses/LICENSE
clickhouse_connect-0.10.0.dist-info/METADATA
clickhouse_connect-0.10.0.dist-info/WHEEL
clickhouse_connect-0.10.0.dist-info/entry_points.txt
clickhouse_connect-0.10.0.dist-info/top_level.txt
clickhouse_connect-0.10.0.dist-info/RECORD
