Metadata-Version: 2.4
Name: clickhouse-connect
Version: 0.10.0
Summary: ClickHouse Database Core Driver for Python, Pandas, and Superset
Home-page: https://github.com/ClickHouse/clickhouse-connect
Author: ClickHouse Inc.
Author-email: clients@clickhouse.com
License: Apache License 2.0
Keywords: clickhouse,superset,sqlalchemy,http,driver
Classifier: Development Status :: 4 - Beta
Classifier: Intended Audience :: Developers
Classifier: License :: OSI Approved :: Apache Software License
Classifier: Programming Language :: Python :: 3.9
Classifier: Programming Language :: Python :: 3.10
Classifier: Programming Language :: Python :: 3.11
Classifier: Programming Language :: Python :: 3.12
Classifier: Programming Language :: Python :: 3.13
Classifier: Programming Language :: Python :: 3.14
Requires-Python: >=3.9,<3.15
License-File: LICENSE
Requires-Dist: certifi
Requires-Dist: urllib3>=1.26
Requires-Dist: pytz
Requires-Dist: zstandard; python_version < "3.14"
Requires-Dist: zstandard>=0.25.0; python_version >= "3.14"
Requires-Dist: lz4; python_version < "3.14"
Requires-Dist: lz4>=4.4.5; python_version >= "3.14"
Provides-Extra: sqlalchemy
Requires-Dist: sqlalchemy<3.0,>=1.4.40; extra == "sqlalchemy"
Provides-Extra: numpy
Requires-Dist: numpy; extra == "numpy"
Provides-Extra: pandas
Requires-Dist: pandas; extra == "pandas"
Provides-Extra: polars
Requires-Dist: polars>=1.0; extra == "polars"
Provides-Extra: arrow
Requires-Dist: pyarrow>=22.0; python_version >= "3.14" and extra == "arrow"
Requires-Dist: pyarrow; python_version < "3.14" and extra == "arrow"
Provides-Extra: orjson
Requires-Dist: orjson; extra == "orjson"
Provides-Extra: tzlocal
Requires-Dist: tzlocal>=4.0; extra == "tzlocal"
Dynamic: author
Dynamic: author-email
Dynamic: classifier
Dynamic: description
Dynamic: description-content-type
Dynamic: home-page
Dynamic: keywords
Dynamic: license
Dynamic: license-file
Dynamic: provides-extra
Dynamic: requires-dist
Dynamic: requires-python
Dynamic: summary
